{"list":[
    {"id":101, "category":1, "nameBook":"Полночь в кафе 'Чёрный дрозд'", "price":20, "author":"Уэббер Хэзер", "image":"img1_1.jpg"},
    {"id":102, "category":1, "nameBook":"Ольга", "price":8, "author":"Бернхард Шлинк", "image":"img1_2.jpg"},
    {"id":103, "category":1, "nameBook":"Где живет счастье", "price":7, "author":"Джоджо Мойес", "image":"img1_3.jpg"},
    {"id":104, "category":1, "nameBook":"Весь невидимый нам свет", "price":9, "author":"Дорр Энтони", "image":"img1_4.jpg"},
    {"id":105, "category":1, "nameBook":"На берегу Рио-Пьедра села я и заплакала", "price":14, "author":"Пауло Коэльо", "image":"img1_5.jpg"},
    {"id":106, "category":1, "nameBook":"Алхимик", "price":19, "author":"Пауло Коэльо", "image":"img1_6.jpg"},
    {"id":107, "category":1, "nameBook":"Спаси меня", "price":11, "author":"Гийом Мюссо", "image":"img1_7.jpg"},
    {"id":108, "category":1, "nameBook":"Прошло семь лет...", "price":11, "author":"Гийом Мюссо", "image":"img1_8.jpg"},
    {"id":109, "category":1, "nameBook":"Тайная книга Данте", "price":23, "author":"Фьоретти Франческо", "image":"img1_9.jpg"},
    {"id":110, "category":1, "nameBook":"Рай где-то рядом", "price":20, "author":"Флэгг Фэнни", "image":"img1_10.jpg"},
    {"id":111, "category":1, "nameBook":"Истории обитателей холмов", "price":17, "author":"Адамс Ричард", "image":"img1_11.jpg"},
    {"id":112, "category":1, "nameBook":"Невидимки", "price":13, "author":"Чак Паланик", "image":"img1_12.jpg"},
    {"id":113, "category":1, "nameBook":"Призраки", "price":13, "author":"Чак Паланик", "image":"img1_13.jpg"},
    {"id":114, "category":1, "nameBook":"Инферно", "price":15, "author":"Браун Дэн", "image":"img1_14.jpg"},
    {"id":115, "category":1, "nameBook":"Последняя камелия", "price":11, "author":"Сара Джио", "image":"img1_15.jpg"},
    {"id":116, "category":1, "nameBook":"Лунная тропа", "price":11, "author":"Сара Джио", "image":"img1_16.jpg"},
    {"id":117, "category":1, "nameBook":"Дерево растет в Бруклине", "price":17, "author":"Смит Бетти", "image":"img1_17.jpg"},
    {"id":118, "category":1, "nameBook":"Ангелы и демоны", "price":10, "author":"Браун Дэн", "image":"img1_18.jpg"},
    {"id":119, "category":1, "nameBook":"Лучшее во мне", "price":12, "author":"Николас Спаркс", "image":"img1_19.jpg"},
    {"id":120, "category":1, "nameBook":"Дневник памяти", "price":12, "author":"Николас Спаркс", "image":"img1_20.jpg"},
    {"id":121, "category":1, "nameBook":"Взгляни на меня", "price":12, "author":"Николас Спаркс", "image":"img1_21.jpg"},
    {"id":122, "category":1, "nameBook":"Тень ветра", "price":28, "author":"Карлос Руис Сафон", "image":"img1_22.jpg"},
    {"id":123, "category":1, "nameBook":"Третий близнец", "price":18, "author":"Кен Фоллетт", "image":"img1_23.jpg"},
    {"id":124, "category":1, "nameBook":"Танцующая на гребне волны", "price":13, "author":"Карен Уайт", "image":"img1_24.jpg"},
    {"id":125, "category":1, "nameBook":"Совершенство", "price":26, "author":"Клэр Норт", "image":"img1_25.jpg"},
    {"id":126, "category":1, "nameBook":"Подземка", "price":9, "author":"Харуки Мураками", "image":"img1_26.jpg"},
    {"id":127, "category":1, "nameBook":"Мужчины без женщин", "price":14, "author":"Харуки Мураками", "image":"img1_27.jpg"},
    {"id":128, "category":1, "nameBook":"Перегрузка", "price":17, "author":"Артур Хейли", "image":"img1_28.jpg"},
    {"id":129, "category":1, "nameBook":"Отель", "price":17, "author":"Артур Хейли", "image":"img1_29.jpg"},
    {"id":130, "category":1, "nameBook":"Аэропорт", "price":17, "author":"Артур Хейли", "image":"img1_30.jpg"},
    {"id":131, "category":1, "nameBook":"Хроники Клифтонов. Книга 1. Лишь время покажет", "price":29, "author":"Джеффри Арчер", "image":"img1_31.jpg"},
    {"id":132, "category":1, "nameBook":"Сентрал-парк", "price":16, "author":"Гийом Мюссо", "image":"img1_32.jpg"},
    {"id":133, "category":1, "nameBook":"Дневник мага", "price":27, "author":"Пауло Коэльо", "image":"img1_33.jpg"},
    {"id":134, "category":1, "nameBook":"Навстречу мечте", "price":25, "author":"Люси Кларк", "image":"img1_34.jpg"},
    {"id":201, "category":2, "nameBook":"Итоговые комплексные работы 2 класс", "price":5, "author":"Узорова О.В.", "image":"img2_1.jpg"},
    {"id":202, "category":2, "nameBook":"Весь курс начальной школы: в схемах и таблицах", "price":23, "author":"Безкоровайная Е.В.", "image":"img2_2.jpg"},
    {"id":203, "category":2, "nameBook":"Итоговые комплексные работы 3 класс", "price":23, "author":"Узорова О.В.", "image":"img2_3.jpg"},
    {"id":204, "category":2, "nameBook":"Сольфеджио 2.0: тесты для самопроверки с ключами", "price":14, "author":"Ремизова Э.Е.", "image":"img2_4.jpg"},
    {"id":205, "category":2, "nameBook":"Программирование на С++ в примерах и задачах", "price":32, "author":"Васильев А.Н.", "image":"img2_5.jpg"},
    {"id":206, "category":2, "nameBook":"Level Up. Твой личный гид в мире компьютерных игр", "price":38, "author":"Джонни Каллен", "image":"img2_6.jpg"},
    {"id":207, "category":2, "nameBook":"JavaScript для начинающих. 6-е издание", "price":38, "author":"МакГрат М.", "image":"img2_7.jpg"},
    {"id":208, "category":2, "nameBook":"Программирование на Python для начинающих", "price":27, "author":"МакГрат М.", "image":"img2_8.jpg"},
    {"id":209, "category":2, "nameBook":"HTML и CSS. Разработка и дизайн веб-сайтов", "price":72, "author":"Дакетт Д.", "image":"img2_9.jpg"},
    {"id":210, "category":2, "nameBook":"Информатика", "price":14, "author":"Тимофеева Е.В.", "image":"img2_10.jpg"},
    {"id":211, "category":2, "nameBook":"Прогроммирование на Java для начинающих", "price":46, "author":"Васильев А.Н.", "image":"img2_11.jpg"},
    {"id":212, "category":2, "nameBook":"Английский язык за 3 месяца. Интенсивный курс", "price":14, "author":"Державина В.А.", "image":"img2_12.jpg"},
    {"id":213, "category":2, "nameBook":"Английский язык. Визуальная граматика для школьников", "price":26, "author":"Меженная А.В.", "image":"img2_13.jpg"},
    {"id":214, "category":2, "nameBook":"Немецкий язык для школьников", "price":26, "author":"Богданова Н.В.", "image":"img2_14.jpg"},
    {"id":215, "category":2, "nameBook":"Английская граматика без репетитора", "price":10, "author":"Державина В.А.", "image":"img2_15.jpg"},
    {"id":216, "category":2, "nameBook":"Англо-русский. Русско-английский словарь", "price":7, "author":"Мюллер В.К.", "image":"img2_16.jpg"},
    {"id":217, "category":2, "nameBook":"Английский разговорник", "price":13, "author":"", "image":"img2_17.jpg"},
    {"id":218, "category":2, "nameBook":"Страноведение. 20-21 век. Великобритания", "price":18, "author":"Козикис", "image":"img2_18.jpg"},
    {"id":219, "category":2, "nameBook":"История. 10 класс. Рабочая тетрадь", "price":6, "author":"Краснова, Панов", "image":"img2_19.jpg"},
    {"id":301, "category":3, "nameBook":"Сновидец. Мистер невозможность", "price":23, "author":"Стивотер М.", "image":"img3_1.jpg"},
    {"id":302, "category":3, "nameBook":"Девушка из кошмаров", "price":4, "author":"Блейк К.", "image":"img3_2.jpg"},
    {"id":303, "category":3, "nameBook":"Стивен Кинг идет в кино", "price":17, "author":"Стивен Кинг", "image":"img3_3.jpg"},
    {"id":304, "category":3, "nameBook":"Академия вампиров. Книга 5. Оковы для призрока", "price":25, "author":"Райчел Мид", "image":"img3_4.jpg"},
    {"id":305, "category":3, "nameBook":"Путь на Амальтею. Далекая радуга", "price":21, "author":"Стругацкий А.Н.", "image":"img3_5.jpg"},
    {"id":306, "category":3, "nameBook":"Кровавые девы", "price":24, "author":"Хэмбли Б.", "image":"img3_6.jpg"},
    {"id":307, "category":3, "nameBook":"Мобильник", "price":29, "author":"Стивен Кинг", "image":"img3_7.jpg"},
    {"id":308, "category":3, "nameBook":"Солярис", "price":57, "author":"Станислав Лем", "image":"img3_8.jpg"},
    {"id":309, "category":3, "nameBook":"Лорд с планеты Земля", "price":28, "author":"Сергей Лукьяненко", "image":"img3_9.jpg"},
    {"id":310, "category":3, "nameBook":"Ночные животные", "price":24, "author":"Эшли Дьюал", "image":"img3_10.jpg"},
    {"id":311, "category":3, "nameBook":"Семьи.net", "price":3, "author":"Дивов О., Емец Д.", "image":"img3_11.jpg"},
    {"id":312, "category":3, "nameBook":"Сильмариллион.", "price":46, "author":"Толкин Д.Р.Р", "image":"img3_12.jpg"},
    {"id":313, "category":3, "nameBook":"Плетеное каралевство", "price":31, "author":"Тахира Мафи", "image":"img3_13.jpg"},
    {"id":314, "category":3, "nameBook":"Тяжелый свет Куртейна. Желтый", "price":26, "author":"Макс Фрай", "image":"img3_14.jpg"},
    {"id":315, "category":3, "nameBook":"Жребий Салема", "price":34, "author":"Стивен Кинг", "image":"img3_15.jpg"},
    {"id":316, "category":3, "nameBook":"Девушка, которая упала в море", "price":25, "author":"Акси О.", "image":"img3_16.jpg"},
    {"id":317, "category":3, "nameBook":"Морфо", "price":24, "author":"Амелия Грэмм", "image":"img3_17.jpg"},
    {"id":318, "category":3, "nameBook":"Одна истинная королева. Книга 1", "price":27, "author":"Дженнифер Бенкау", "image":"img3_18.jpg"},
    {"id":319, "category":3, "nameBook":"Хоббит", "price":36, "author":"Толкин Д.Р.Р.", "image":"img3_19.jpg"},
    {"id":320, "category":3, "nameBook":"Одиссей Фокс. Тени звезд", "price":21, "author":"Антон Карелин", "image":"img3_20.jpg"},
    {"id":401, "category":4, "nameBook":"Яблоки на снегу", "price":18, "author":"Андрей Дементьев", "image":"img4_1.jpg"},
    {"id":402, "category":4, "nameBook":"Я вас любил", "price":31, "author":"Александр Пушкин", "image":"img4_2.jpg"},
    {"id":403, "category":4, "nameBook":"Клен ты мой опавший...", "price":8, "author":"Сергей Есенин", "image":"img4_3.jpg"},
    {"id":404, "category":4, "nameBook":"Избранное", "price":18, "author":"Эдуард Асадов", "image":"img4_4.jpg"},
    {"id":405, "category":4, "nameBook":"Путешествие дилетантов", "price":15, "author":"Булат Акуджава", "image":"img4_5.jpg"},
    {"id":406, "category":4, "nameBook":"За это можно все отдать", "price":20, "author":"Вероника Тушнова", "image":"img4_6.jpg"},
    {"id":407, "category":4, "nameBook":"Вчера еще в глаза глядел...", "price":20, "author":"Марина Цветаева", "image":"img4_7.jpg"},
    {"id":408, "category":4, "nameBook":"Столько просьб у любимой всегда...", "price":20, "author":"Анна Ахматова", "image":"img4_8.jpg"},
    {"id":409, "category":4, "nameBook":"Я не верю судьбе", "price":20, "author":"Владимир Высоцкий", "image":"img4_9.jpg"},
    {"id":410, "category":4, "nameBook":"Бег времени", "price":22, "author":"Анна Ахматова", "image":"img4_10.jpg"},
    {"id":411, "category":4, "nameBook":"Стихотворения. Поэмы", "price":34, "author":"Сергей Есенин", "image":"img4_11.jpg"},
    {"id":412, "category":4, "nameBook":"Стихотворения", "price":30, "author":"Александр Блок", "image":"img4_12.jpg"},
    {"id":413, "category":4, "nameBook":"Стихотворения", "price":30, "author":"Федор Тютчев", "image":"img4_13.jpg"},
    {"id":414, "category":4, "nameBook":"Лирика", "price":30, "author":"Борис Пастернак", "image":"img4_14.jpg"},
    {"id":415, "category":4, "nameBook":"Признание в любви", "price":30, "author":"Лариса Рубальская", "image":"img4_15.jpg"},
    {"id":416, "category":4, "nameBook":"Большое собрание стихотворений и поэм в одном томе", "price":27, "author":"Владимир Маяковский", "image":"img4_16.jpg"},
    {"id":417, "category":4, "nameBook":"Рубаи", "price":30, "author":"Омар Хайям", "image":"img4_17.jpg"},
    {"id":418, "category":4, "nameBook":"Лирика серебрянного века", "price":30, "author":"Гумилев Н.С.", "image":"img4_18.jpg"},
    {"id":419, "category":4, "nameBook":"Рубаи", "price":30, "author":"Омар Хайям", "image":"img4_19.jpg"},
    {"id":420, "category":4, "nameBook":"Эхо любви", "price":14, "author":"Роберт Рождественский", "image":"img4_20.jpg"},
    {"id":421, "category":4, "nameBook":"Стихотворения и поэмы", "price":14, "author":"Михоил Лермонтов", "image":"img4_21.jpg"},
    {"id":422, "category":4, "nameBook":"Лунный свет", "price":14, "author":"Яков Полонский", "image":"img4_22.jpg"},
    {"id":501, "category":5, "nameBook":"Математика с Григорием Остером", "price":24, "author":"Остер Григорий", "image":"img5_1.jpg"},
    {"id":502, "category":5, "nameBook":"Головоломки. Задачи. Фокусы. Развлечения", "price":9, "author":"Яков Перельман", "image":"img5_2.jpg"},
    {"id":503, "category":5, "nameBook":"Зачетные головоломки", "price":6, "author":"Ирина Ремезова", "image":"img5_3.jpg"},
    {"id":504, "category":5, "nameBook":"Волшебные окошки. Динозавры", "price":28, "author":"", "image":"img5_4.jpg"},
    {"id":505, "category":5, "nameBook":"Страна роботов. Найди и покажи", "price":19, "author":"Томаш Коваль", "image":"img5_5.jpg"},
    {"id":506, "category":5, "nameBook":"Самые важные знания", "price":22, "author":"", "image":"img5_6.jpg"},
    {"id":507, "category":5, "nameBook":"Волшебные окошки. Техника", "price":28, "author":"", "image":"img5_7.jpg"},
    {"id":508, "category":5, "nameBook":"Уроки правильной речи и правильного мышления", "price":15, "author":"Надежда Жукова", "image":"img5_8.jpg"},
    {"id":509, "category":5, "nameBook":"Кошки и собаки", "price":15, "author":"Юлия Дорошенко", "image":"img5_9.jpg"},
    {"id":510, "category":5, "nameBook":"Зоопарк", "price":15, "author":"Юлия Дорошенко", "image":"img5_10.jpg"},
    {"id":511, "category":5, "nameBook":"Буквограмма. От 3 до 6", "price":21, "author":"Светлана Шишкова", "image":"img5_11.jpg"},
    {"id":512, "category":5, "nameBook":"Весь мир животных", "price":19, "author":"Людмила Доманская", "image":"img5_12.jpg"},
    {"id":513, "category":5, "nameBook":"В мире животных. Стикербук", "price":32, "author":"Миранда Левер", "image":"img5_13.jpg"},
    {"id":514, "category":5, "nameBook":"День Рождения. Учимся говорить вежливо", "price":35, "author":"", "image":"img5_14.jpg"},
    {"id":515, "category":5, "nameBook":"Разноцветная мозайка для малышей", "price":15, "author":"", "image":"img5_15.jpg"},
    {"id":516, "category":5, "nameBook":"Формула добра. Приключения необычной собаки", "price":15, "author":"Михаил Самарский", "image":"img5_16.jpg"},
    {"id":517, "category":5, "nameBook":"Тришка на севере", "price":16, "author":"Михаил Самарский", "image":"img5_17.jpg"},
    {"id":518, "category":5, "nameBook":"Сэр Мартин. Возвращение на родину", "price":17, "author":"Михаил Самарский", "image":"img5_18.jpg"},
    {"id":519, "category":5, "nameBook":"Как Трисон стал полицейским, или правила добрых дел", "price":15, "author":"Михаил Самарский", "image":"img5_19.jpg"},
    {"id":520, "category":5, "nameBook":"Дядя Федор, пес и кот в деревне Простоквашино", "price":24, "author":"Эдуард Успенский", "image":"img5_20.jpg"},
    {"id":521, "category":5, "nameBook":"Борьба Иви", "price":24, "author":"Холли Вебб", "image":"img5_21.jpg"},
    {"id":522, "category":5, "nameBook":"Котенок Одуванчик, или игра в прятки", "price":12, "author":"Холли Вэбб", "image":"img5_22.jpg"},
    {"id":523, "category":5, "nameBook":"Стихи и сказки", "price":7, "author":"Борис Заходер", "image":"img5_23.jpg"},
    {"id":524, "category":5, "nameBook":"Мойдодыр и другие сказки", "price":9, "author":"Корней Чуковский", "image":"img5_24.jpg"},
    {"id":525, "category":5, "nameBook":"Айболит", "price":10, "author":"Корней Чуковский", "image":"img5_25.jpg"},
    {"id":526, "category":5, "nameBook":"Пес по имени Шторм", "price":19, "author":"Холли Вебб", "image":"img5_26.jpg"},
    {"id":527, "category":5, "nameBook":"Девочка с портрета", "price":21, "author":"Холли Вебб", "image":"img5_27.jpg"},
    {"id":528, "category":5, "nameBook":"Волшебная фигурка", "price":20, "author":"Холли Вебб", "image":"img5_28.jpg"},
    {"id":529, "category":5, "nameBook":"Утраченное сокровище", "price":28, "author":"Холли Вебб", "image":"img5_29.jpg"},
    {"id":601, "category":6, "nameBook":"Большой иллюстрированный атлас мира", "price":34, "author":"", "image":"img6_1.jpg"},
    {"id":602, "category":6, "nameBook":"Танки мира", "price":30, "author":"", "image":"img6_2.jpg"},
    {"id":603, "category":6, "nameBook":"Большая энциклопедия монет", "price":37, "author":"", "image":"img6_3.jpg"},
    {"id":604, "category":6, "nameBook":"Иллюстрированный атлас географических открытий", "price":35, "author":"", "image":"img6_4.jpg"},
    {"id":605, "category":6, "nameBook":"Животный мир. Иллюстрированный атлас", "price":35, "author":"", "image":"img6_5.jpg"},
    {"id":606, "category":6, "nameBook":"Большая иллюстрированная энциклопедия. Атлас мира. Политические и физические карты", "price":34, "author":"", "image":"img6_6.jpg"},
    {"id":607, "category":6, "nameBook":"Вселенная. Иллюстрированный атлас", "price":37, "author":"Марк Гарлик", "image":"img6_7.jpg"},
    {"id":608, "category":6, "nameBook":"Динозавры. Иллюстрированный атлас", "price":36, "author":"", "image":"img6_8.jpg"},
    {"id":609, "category":6, "nameBook":"Иллюстрированный атлас мира", "price":33, "author":"", "image":"img6_9.jpg"},
    {"id":610, "category":6, "nameBook":"Океаны. Иллюстрированный атлас", "price":36, "author":"Стивен Хатчинсон", "image":"img6_10.jpg"},
    {"id":611, "category":6, "nameBook":"Самые известные танки мира", "price":27, "author":"Вячеслав Шпаковский", "image":"img6_11.jpg"},
    {"id":612, "category":6, "nameBook":"Самые известные самолеты мира", "price":27, "author":"Андрей Мерников", "image":"img6_12.jpg"},
    {"id":701, "category":7, "nameBook":"Английский разговорник", "price":7, "author":"", "image":"img7_1.jpg"},
    {"id":702, "category":7, "nameBook":"Большой русско-белорусский словарь", "price":12, "author":"Купрись Полина", "image":"img7_2.jpg"},
    {"id":703, "category":7, "nameBook":"Целебные травы", "price":5, "author":"Татьяна Ильина", "image":"img7_3.jpg"},
    {"id":704, "category":7, "nameBook":"Английский за 30 дней", "price":15, "author":"Сергей Матвеев", "image":"img7_4.jpg"},
    {"id":705, "category":7, "nameBook":"Польский за 30 дней", "price":13, "author":"", "image":"img7_5.jpg"},
    {"id":706, "category":7, "nameBook":"Рецепты для здоровья и красоты", "price":6, "author":"Сергей Малозёмов", "image":"img7_6.jpg"},
    {"id":707, "category":7, "nameBook":"Медицина здоровья против медицины болезней. Другой путь", "price":7, "author":"Александр Шишонин", "image":"img7_7.jpg"}
]}